ytdlbt/__init__.py
ytdlbt/ytdlbt.py
ytdlft/__init__.py
ytdlft/ytdlft.py
ytdlbt-1.0.7.dist-info/METADATA
ytdlbt-1.0.7.dist-info/WHEEL
ytdlbt-1.0.7.dist-info/top_level.txt
ytdlbt-1.0.7.dist-info/RECORD
