Metadata-Version: 2.1
Name: ytdlbt
Version: 1.0.7
Summary: download youtube music by title
Home-page: UNKNOWN
Author: insu
Author-email: kin4496@naver.com
License: MIT
Platform: UNKNOWN
Requires-Python: >=3.*
Requires-Dist: pytube
Requires-Dist: youtube-search-python
Requires-Dist: librosa
Requires-Dist: numpy
Requires-Dist: matplotlib
